ewatercycle_model_testing/PluginOwnerRunVisualisation.py
ewatercycle_model_testing/PluginOwnerVisualisationUI.py
ewatercycle_model_testing/__init__.py
ewatercycle_model_testing/bmi_spec_tests.py
ewatercycle_model_testing/constants.py
ewatercycle_model_testing/error_tests.py
ewatercycle_model_testing/main.py
ewatercycle_model_testing/metric_tests.py
ewatercycle_model_testing/mocks.py
ewatercycle_model_testing/parse_submission.py
ewatercycle_model_testing/plugin_owner_run_tests.py
ewatercycle_model_testing/plugin_owner_test_ui.py
ewatercycle_model_testing/pull_check.py
ewatercycle_model_testing/run_model_util.py
ewatercycle_model_testing/scenario_tests.py
ewatercycle_model_testing/scenarios_util.py
ewatercycle_model_testing/spec_tests.py
ewatercycle_model_testing/test.py
ewatercycle_model_testing/test_bank.py
ewatercycle_model_testing/test_report_maker.py
ewatercycle_model_testing/test_result.py
ewatercycle_model_testing/test_suite.py
ewatercycle_model_testing/TestingModelsAndData/RunAndPlotPCRGLOB.py
ewatercycle_model_testing/TestingModelsAndData/TestObservationData.py
ewatercycle_model_testing/TestingModelsAndData/__init__.py
ewatercycle_model_testing-0.0.1.dist-info/LICENSE
ewatercycle_model_testing-0.0.1.dist-info/METADATA
ewatercycle_model_testing-0.0.1.dist-info/WHEEL
ewatercycle_model_testing-0.0.1.dist-info/top_level.txt
ewatercycle_model_testing-0.0.1.dist-info/RECORD
