Metadata-Version: 2.1
Name: ewatercycle-model-testing
Version: 0.0.1
Summary: Comprehensive and flexible testing framework for hydrological model plugins that intend to integrate with the eWaterCycle platform.
Author: Ferdi Helvensteijn, Konrad Gniaź, Alexander van den Arend Schmidt, Robert Mertens, Floris van der Voorn
Author-email: a.f.helvensteijn@student.tudelft.nl, k.gniaz@student.tudelft.nl, a.f.vandenarendschmidt@student.tudelft.nl, r.h.mertens@student.tudelft.nl, f.c.g.vandervoorn@student.tudelft.nl
License: Apache-2.0
Classifier: Programming Language :: Python :: 3
Classifier: License :: OSI Approved :: Apache Software License
Requires-Python: >=3.10
License-File: LICENSE
Requires-Dist: PyYAML ==6.0.1
Requires-Dist: ewatercycle ~=2.1.0
Requires-Dist: ewatercycle-hype ==0.0.1
Requires-Dist: ewatercycle-leakybucket ==0.0.2
Requires-Dist: ewatercycle-lisflood ==0.0.1
Requires-Dist: ewatercycle-marrmot ==0.0.2
Requires-Dist: ewatercycle-pcrglobwb ==0.0.2
Requires-Dist: ewatercycle-wflow ==0.0.2
Requires-Dist: markdown2 ~=2.4.13
Requires-Dist: Cython ~=3.0.10
Requires-Dist: netCDF4 ~=1.6.5
Requires-Dist: ttkbootstrap ~=1.10.1
Requires-Dist: xarray ~=2024.5.0
Requires-Dist: era5cli ==1.4.2
Provides-Extra: dev
Requires-Dist: pytest ~=8.2.0 ; extra == 'dev'
Requires-Dist: pylint ==3.2.3 ; extra == 'dev'
Requires-Dist: isort ==5.13.2 ; extra == 'dev'
